scraper/__init__.py
scraper/command/cli.py
scraper/command/services.py
scraper/debug.py
scraper/extractor.py
scraper/rei.py
scraper/runner.py
scraper/utils/__init.py
scraper/utils/validation.py
reiscraper-0.1.0.dist-info/METADATA
reiscraper-0.1.0.dist-info/WHEEL
reiscraper-0.1.0.dist-info/RECORD
