Metadata-Version: 2.1
Name: reiScraper
Version: 0.1.0
Summary: Rei Scrapper
License: MIT
Author: Lutfi Verdian
Requires-Python: >=3.10,<4.0
Classifier: License :: OSI Approved :: MIT License
Classifier: Programming Language :: Python :: 3
Classifier: Programming Language :: Python :: 3.10
Classifier: Programming Language :: Python :: 3.11
Classifier: Programming Language :: Python :: 3.12
Requires-Dist: httpx (>=0.26.0,<0.27.0)
Requires-Dist: rich (>=13.7.0,<14.0.0)
Requires-Dist: selectolax (>=0.3.17,<0.4.0)
Requires-Dist: typing (>=3.12.1,<4.0.0)
